Metadata-Version: 1.1
Name: pyjstore
Version: 0.0.1
Summary: client library for dynamodb as a json store
Home-page: https://github.com/xitter/dynamo-store
Author: Vijay Jain
Author-email: mnnit.vijay@gmail.com
License: MIT
Keywords: dynamo,json,dump
Platform: UNKNOWN
Classifier: Development Status :: 3 - Alpha
Classifier: Intended Audience :: Developers
Classifier: License :: OSI Approved :: MIT License
Classifier: Programming Language :: Python :: 3.4
Classifier: Programming Language :: Python :: 3.5
